mentorhub_utils/__init__.py
mentorhub_utils/config/MentorHub_Config.py
mentorhub_utils/config/__init__.py
mentorhub_utils/config/config_routes.py
mentorhub_utils/config/test_config_defaults.py
mentorhub_utils/config/test_config_env.py
mentorhub_utils/config/test_config_file.py
mentorhub_utils/config/test_config_routes.py
mentorhub_utils/flask_utils/__init__.py
mentorhub_utils/flask_utils/breadcrumb.py
mentorhub_utils/flask_utils/ejson_encoder.py
mentorhub_utils/flask_utils/test_breadcrumb.py
mentorhub_utils/flask_utils/test_token.py
mentorhub_utils/flask_utils/token.py
mentorhub_utils/mongo_utils/__init__.py
mentorhub_utils/mongo_utils/encode_properties.py
mentorhub_utils/mongo_utils/mentorhub_mongo_io.py
mentorhub_utils/mongo_utils/test_encode_properties.py
mentorhub_utils/mongo_utils/testwithbacking_mentorhub_mongo_io.py
mentorhub_utils-1.1.0.dist-info/licenses/LICENSE
mentorhub_utils-1.1.0.dist-info/METADATA
mentorhub_utils-1.1.0.dist-info/WHEEL
mentorhub_utils-1.1.0.dist-info/top_level.txt
mentorhub_utils-1.1.0.dist-info/RECORD
