Metadata-Version: 2.4
Name: mentorhub-utils
Version: 1.1.0
Summary: Helper utilities for Mentorhub API projects
Home-page: https://github.com/agile-learning-institute/mentorHub-utils
Author: Agile Learning Institute
Author-email: devs@agile-learning.institute
License: Apache-2.0
Classifier: Programming Language :: Python :: 3
Classifier: License :: OSI Approved :: Apache Software License
Classifier: Operating System :: OS Independent
Requires-Python: >=3.6
License-File: LICENSE
Requires-Dist: flask
Requires-Dist: pymongo
Requires-Dist: joserfc
Dynamic: author
Dynamic: author-email
Dynamic: classifier
Dynamic: description
Dynamic: description-content-type
Dynamic: home-page
Dynamic: license
Dynamic: license-file
Dynamic: requires-dist
Dynamic: requires-python
Dynamic: summary
